iic_guard/_c_iic_guard.cpython-312-x86_64-linux-gnu.so
iic_guard/c_wrapper.py
iic_guard/config.py
iic_guard/guard.py
iic_guard/main.py
iic_guard/c_src/iic_guard.c
iic_guard-0.1.0.dist-info/LICENSE
iic_guard-0.1.0.dist-info/METADATA
iic_guard-0.1.0.dist-info/WHEEL
iic_guard-0.1.0.dist-info/entry_points.txt
iic_guard-0.1.0.dist-info/top_level.txt
iic_guard-0.1.0.dist-info/RECORD
