Metadata-Version: 2.1
Name: iic-guard
Version: 0.1.0
Summary: A daemon to monitor and protect I2C device registers.
Author-email: Serhat Urtis <urtisms@gmail.com>
License: MIT License
Project-URL: Homepage, https://github.com/serhaturtis/iic-guard
Project-URL: Bug Tracker, https://github.com/serhaturtis/iic-guard/issues
Classifier: Programming Language :: Python :: 3
Classifier: Operating System :: POSIX :: Linux
Requires-Python: >=3.7
License-File: LICENSE
Requires-Dist: pydantic
Requires-Dist: pyyaml
Requires-Dist: python-daemon
